{
  "categories": [
    {
      "name": "Phase Tags",
      "description": "Phase identification tags",
      "required": true,
      "tags": [
        {
          "name": "@high",
          "description": "High priority features that should be implemented early"
        }
      ]
    },
    {
      "name": "Component Tags",
      "description": "Architectural component tags",
      "required": true,
      "tags": [
        {
          "name": "@api",
          "description": "API integration and networking components"
        },
        {
          "name": "@app",
          "description": "Application-level components and root layout"
        },
        {
          "name": "@infrastructure",
          "description": "Infrastructure and setup-related components"
        },
        {
          "name": "@services",
          "description": "Service layer and business logic"
        },
        {
          "name": "@ui",
          "description": "User interface and visual components"
        }
      ]
    },
    {
      "name": "Feature Group Tags",
      "description": "Functional area tags",
      "required": true,
      "tags": [
        {
          "name": "@api-integration",
          "description": "API integration and external service connectivity"
        },
        {
          "name": "@dependency-management",
          "description": "Package and dependency management features"
        },
        {
          "name": "@feature-home",
          "description": "Home screen features including search and track listing"
        },
        {
          "name": "@state-management",
          "description": "State management and Redux integration features"
        }
      ]
    },
    {
      "name": "Technical Tags",
      "description": "Technical concern tags",
      "required": false,
      "tags": [
        {
          "name": "@configuration",
          "description": "Configuration files and environment setup"
        },
        {
          "name": "@environment",
          "description": "Environment variables and runtime configuration"
        },
        {
          "name": "@monorepo",
          "description": "Monorepo-specific features and configurations"
        },
        {
          "name": "@redux",
          "description": "Redux and Redux Toolkit implementation"
        },
        {
          "name": "@rtk-query",
          "description": "Redux Toolkit Query for API state management"
        },
        {
          "name": "@typescript",
          "description": "TypeScript type definitions and interfaces"
        }
      ]
    },
    {
      "name": "Platform Tags",
      "description": "Platform-specific tags",
      "required": false,
      "tags": [
        {
          "name": "@expo",
          "description": "Expo-specific features and functionality"
        },
        {
          "name": "@react-native",
          "description": "React Native mobile platform features"
        }
      ]
    },
    {
      "name": "Priority Tags",
      "description": "Implementation priority tags",
      "required": false,
      "tags": [
        {
          "name": "@high",
          "description": "High priority features requiring early implementation"
        }
      ]
    },
    {
      "name": "Status Tags",
      "description": "Development status tags",
      "required": false,
      "tags": [
        {
          "name": "@done",
          "description": "Completed and verified features"
        },
        {
          "name": "@setup",
          "description": "Setup and initialization work in progress"
        }
      ]
    },
    {
      "name": "Testing Tags",
      "description": "Test-related tags",
      "required": false,
      "tags": []
    },
    {
      "name": "Automation Tags",
      "description": "Automation integration tags",
      "required": false,
      "tags": []
    }
  ],
  "combinationExamples": [],
  "usageGuidelines": {
    "requiredCombinations": {
      "title": "",
      "requirements": [],
      "minimumExample": ""
    },
    "recommendedCombinations": {
      "title": "",
      "includes": [],
      "recommendedExample": ""
    },
    "orderingConvention": {
      "title": "",
      "order": [],
      "example": ""
    }
  },
  "addingNewTags": {
    "process": [],
    "namingConventions": [],
    "antiPatterns": {
      "dont": [],
      "do": []
    }
  },
  "queries": {
    "title": "",
    "examples": []
  },
  "statistics": {
    "lastUpdated": "2025-11-21T11:38:08.504Z",
    "phaseStats": [],
    "componentStats": [],
    "featureGroupStats": [],
    "updateCommand": "fspec tag-stats"
  },
  "validation": {
    "rules": [],
    "commands": []
  },
  "references": []
}
